README
setup.py
TracSphinx.egg-info/PKG-INFO
TracSphinx.egg-info/SOURCES.txt
TracSphinx.egg-info/dependency_links.txt
TracSphinx.egg-info/entry_points.txt
TracSphinx.egg-info/namespace_packages.txt
TracSphinx.egg-info/requires.txt
TracSphinx.egg-info/top_level.txt
tracext/__init__.py
tracext/sphinx/__init__.py
tracext/sphinx/main.py