Metadata-Version: 1.0
Name: TracSphinx
Version: 0.2
Summary: Sphinx plugin for Trac 0.11
Home-page: http://bitbucket.org/florent/sphinx-plugin
Author: Florent PIGOUT
Author-email: florent.pigout@gmail.com
License: BSD
Keywords: trac plugin sphinx
Platform: UNKNOWN
